src/__init__.py
src/archive.py
src/cli.py
src/unarchive.py
easy_archive-0.0.2.dist-info/LICENSE
easy_archive-0.0.2.dist-info/METADATA
easy_archive-0.0.2.dist-info/WHEEL
easy_archive-0.0.2.dist-info/entry_points.txt
easy_archive-0.0.2.dist-info/top_level.txt
easy_archive-0.0.2.dist-info/RECORD
