Metadata-Version: 2.1
Name: easy-archive
Version: 0.0.2
Summary: Easy Archive is a tool to archive and compress files and directories, especially for large a lot of files.
Home-page: https://github.com/jdf-prog/easy-archive
Author: Dongfu Jiang
Author-email: dongfu.jiang@uwaterloo.ca
License-File: LICENSE
Requires-Dist: datasets
Requires-Dist: fire
Requires-Dist: matplotlib
Requires-Dist: pandas
Requires-Dist: tqdm
